propertyextractor.py
readin.py
writeout.py
PropertyExtract-1.2.data/scripts/propertyextract
PropertyExtract-1.2.dist-info/LICENSE
PropertyExtract-1.2.dist-info/METADATA
PropertyExtract-1.2.dist-info/WHEEL
PropertyExtract-1.2.dist-info/top_level.txt
PropertyExtract-1.2.dist-info/RECORD
