Metadata-Version: 2.1
Name: PropertyExtract
Version: 1.2
Summary: "PropertyExtract -- LLM-based model to extract material property from unstructured dataset",
Home-page: https://sourceforge.net/projects/propertyextract/
Author: Chinedu Ekuma
Author-email: cekuma1@gmail.com
License: GNU GPL version 3
License-File: LICENSE
Requires-Dist: numpy
Requires-Dist: scipy
Requires-Dist: matplotlib
Requires-Dist: pandas
Requires-Dist: spglib
Requires-Dist: mendeleev
Requires-Dist: openai
Requires-Dist: nltk
Requires-Dist: spacy
Requires-Dist: urllib3
Requires-Dist: textblob
Requires-Dist: google-generativeai
Requires-Dist: backoff
Requires-Dist: chardet
